ipylivebash/__init__.py
ipylivebash/_frontend.py
ipylivebash/_version.py
ipylivebash/debounce.py
ipylivebash/livemagic.py
ipylivebash/logfile.py
ipylivebash/logview.py
ipylivebash/runner.py
ipylivebash/runtask.py
ipylivebash/session.py
ipylivebash/sessionmanager.py
ipylivebash/utils.py
ipylivebash/labextension/package.json
ipylivebash/labextension/static/367.4bb9363e106127fa6b6b.js
ipylivebash/labextension/static/367.4bb9363e106127fa6b6b.js.LICENSE.txt
ipylivebash/labextension/static/367.7b0ec5fa286a4cd786dc.js
ipylivebash/labextension/static/367.7b0ec5fa286a4cd786dc.js.LICENSE.txt
ipylivebash/labextension/static/367.b54502571f1c622ef3e3.js
ipylivebash/labextension/static/367.b54502571f1c622ef3e3.js.LICENSE.txt
ipylivebash/labextension/static/367.d3a8a0e79a5463ac0cdd.js
ipylivebash/labextension/static/367.d3a8a0e79a5463ac0cdd.js.LICENSE.txt
ipylivebash/labextension/static/367.ff0f6ce690046c781ce4.js
ipylivebash/labextension/static/367.ff0f6ce690046c781ce4.js.LICENSE.txt
ipylivebash/labextension/static/480.e6446a30d6b6a16ad121.js
ipylivebash/labextension/static/568.fb1e61d7b0a27a69428e.js
ipylivebash/labextension/static/remoteEntry.2b946155b703617a2fc1.js
ipylivebash/labextension/static/remoteEntry.472b63014fd86835a620.js
ipylivebash/labextension/static/remoteEntry.507ece81300c66ab0764.js
ipylivebash/labextension/static/remoteEntry.5599aab4a597827c7773.js
ipylivebash/labextension/static/remoteEntry.aca2eb28d1e7d8294832.js
ipylivebash/labextension/static/style.js
ipylivebash/labextension/static/third-party-licenses.json
ipylivebash/nbextension/extension.js
ipylivebash/nbextension/index.js
ipylivebash/nbextension/index.js.LICENSE.txt
ipylivebash/nbextension/index.js.map
ipylivebash/tests/__init__.py
ipylivebash/tests/conftest.py
ipylivebash/tests/test_logfile.py
ipylivebash/tests/test_logview.py
ipylivebash/tests/test_nbextension_path.py
ipylivebash/tests/test_runner.py
ipylivebash/tests/test_session.py
ipylivebash/tests/test_sessionmanager.py
ipylivebash-0.2.2.dist-info/LICENSE.txt
ipylivebash-0.2.2.dist-info/METADATA
ipylivebash-0.2.2.dist-info/WHEEL
ipylivebash-0.2.2.dist-info/top_level.txt
ipylivebash-0.2.2.dist-info/RECORD
